{
  "id": 57148016,
  "first_name": "Ion",
  "last_name": "Gheorghe",
  "birth_date": "1999-10-08",
  "country_id": 790,
  "club_id": 57065222,
  "positions": [
    {
      "code": "MC",
      "level": 20
    },
    {
      "code": "AML",
      "level": 20
    },
    {
      "code": "AMC",
      "level": 20
    }
  ],
  "foots": {
    "left": 50,
    "right": 100
  },
  "current_ability": 100,
  "potential_ability": 126,
  "value": 315000,
  "contract": {    "expiration": "2026-06-30",
    "started": "2025-07-01",
    "contract_type": "FullTime"
  },
  "ids": {
    "transfermarkt.com": "436075"
  }
}