{
  "id": 62239648,
  "first_name": "Vukašin",
  "last_name": "Bogdanović",
  "birth_date": "2002-10-04",
  "country_id": 802,
  "club_id": 5748006,
  "positions": [
    {
      "code": "ST",
      "level": 20
    }
  ],
  "foots": {
    "left": 40,
    "right": 100
  },
  "current_ability": 106,
  "potential_ability": 118,
  "value": 517000,
  "contract": {    "expiration": "2027-06-30",
    "started": "2025-07-01",
    "contract_type": "FullTime"
  },
  "ids": {
    "transfermarkt.com": "636567"
  }
}