{
  "id": 2000503220,
  "first_name": "Rubén",
  "last_name": "Bravo",
  "birth_date": "2009-03-15",
  "country_id": 796,
  "club_id": 1733,
  "positions": [
    {
      "code": "AMR",
      "level": 20
    },
    {
      "code": "ST",
      "level": 20
    }
  ],
  "current_ability": 81,
  "potential_ability": 131,
  "value": 489000,
  "contract": {    "expiration": "2028-06-30",
    "started": "2025-07-01",
    "contract_type": "FullTime"
  },
  "loan": {
    "to_club_id": 67276729,
    "expiration": "2027-06-30",    "wage_contribution_pct": 100
  }
}