{
  "id": 2000456939,
  "first_name": "Ruslan",
  "last_name": "Pichienko",
  "birth_date": "2008-04-23",
  "country_id": 791,
  "club_id": 1529,
  "positions": [
    {
      "code": "GK",
      "level": 20
    }
  ],
  "foots": {
    "left": 50,
    "right": 100
  },
  "current_ability": 70,
  "potential_ability": -75,
  "value": 431000,
  "contract": {    "expiration": "2028-12-10",
    "started": "2025-07-01",
    "contract_type": "FullTime"
  },
  "ids": {
    "transfermarkt.com": "1123141"
  }
}