{
  "id": 78064511,
  "first_name": "David",
  "last_name": "Terans",
  "birth_date": "1994-08-11",
  "country_id": 1657,
  "club_id": 323,
  "positions": [
    {
      "code": "AML",
      "level": 20
    },
    {
      "code": "AMC",
      "level": 20
    },
    {
      "code": "ST",
      "level": 20
    }
  ],
  "foots": {
    "left": 100,
    "right": 40
  },
  "current_ability": 122,
  "potential_ability": 136,
  "value": 1000000,
  "contract": {    "expiration": "2026-12-31",
    "started": "2025-07-01",
    "contract_type": "FullTime"
  },
  "ids": {
    "transfermarkt.com": "261309"
  }
}