{
  "id": 2000095400,
  "first_name": "Bruno",
  "last_name": "Melnis",
  "birth_date": "2004-01-21",
  "country_id": 777,
  "club_id": 8404703,
  "positions": [
    {
      "code": "AMR",
      "level": 20
    },
    {
      "code": "AML",
      "level": 20
    },
    {
      "code": "ST",
      "level": 20
    }
  ],
  "foots": {
    "left": 45,
    "right": 100
  },
  "current_ability": 76,
  "potential_ability": 98,
  "value": 103000,
  "contract": {    "expiration": "2026-11-30",
    "started": "2025-07-01",
    "contract_type": "FullTime"
  },
  "ids": {
    "transfermarkt.com": "806968"
  }
}