{
  "id": 2000263996,
  "first_name": "Riquelme",
  "last_name": "Fillipi",
  "birth_date": "2006-09-15",
  "country_id": 1651,
  "club_id": 329,
  "positions": [
    {
      "code": "AMR",
      "level": 20
    },
    {
      "code": "AML",
      "level": 20
    }
  ],
  "foots": {
    "left": 50,
    "right": 100
  },
  "current_ability": 98,
  "potential_ability": -75,
  "value": 2000000,
  "contract": {    "expiration": "2029-12-31",
    "started": "2025-07-01",
    "contract_type": "FullTime"
  },
  "ids": {
    "transfermarkt.com": "1124298"
  }
}