{
  "id": 43090555,
  "first_name": "Ivica",
  "last_name": "Ivušić",
  "birth_date": "1995-02-01",
  "country_id": 761,
  "club_id": 433,
  "positions": [
    {
      "code": "GK",
      "level": 20
    }
  ],
  "foots": {
    "left": 35,
    "right": 100
  },
  "current_ability": 112,
  "potential_ability": 126,
  "value": 875000,
  "contract": {    "expiration": "2029-06-30",
    "started": "2025-07-01",
    "contract_type": "FullTime"
  },
  "ids": {
    "transfermarkt.com": "160482"
  }
}