{
  "id": 67196262,
  "first_name": "Carles",
  "last_name": "Soria",
  "birth_date": "1996-10-08",
  "country_id": 796,
  "club_id": 36136195,
  "positions": [
    {
      "code": "DR",
      "level": 20
    },
    {
      "code": "WBR",
      "level": 20
    },
    {
      "code": "MR",
      "level": 20
    }
  ],
  "foots": {
    "left": 50,
    "right": 100
  },
  "current_ability": 116,
  "potential_ability": 126,
  "value": 2000000,
  "contract": {    "expiration": "2027-06-30",
    "started": "2025-07-01",
    "contract_type": "FullTime"
  },
  "ids": {
    "transfermarkt.com": "376484"
  },
  "history": [
    { "s": 2021, "c": 2390, "p": 24 },
    { "s": 2025, "c": 36136195, "p": 21 }
  ]
}