{
  "id": 2000304361,
  "first_name": "Artúr",
  "last_name": "Musák",
  "birth_date": "2005-10-17",
  "country_id": 794,
  "club_id": 1300301,
  "positions": [
    {
      "code": "MC",
      "level": 20
    },
    {
      "code": "AMC",
      "level": 20
    }
  ],
  "foots": {
    "left": 50,
    "right": 100
  },
  "current_ability": 96,
  "potential_ability": -7,
  "value": 863000,
  "contract": {    "expiration": "2030-06-30",
    "started": "2025-07-01",
    "contract_type": "FullTime"
  },
  "ids": {
    "transfermarkt.com": "1153662"
  }
}