{
  "id": 2000521574,
  "first_name": "Nikolas",
  "last_name": "Hořínek",
  "birth_date": "2009-01-04",
  "country_id": 763,
  "club_id": 1300301,
  "positions": [
    {
      "code": "GK",
      "level": 20
    }
  ],
  "foots": {
    "left": 55,
    "right": 100
  },
  "current_ability": 60,
  "potential_ability": -65,
  "value": 234000,
  "contract": {    "expiration": "2028-06-30",
    "started": "2025-07-01",
    "contract_type": "FullTime"
  },
  "loan": {
    "to_club_id": 136152,
    "expiration": "2027-06-30",    "wage_contribution_pct": 100
  }
}