{
  "id": 5261741,
  "name": "La Equidad",
  "location": {
    "city_id": 1511
  },
  "finance": {
    "balance": 3175000
  },
  "teams": [
    {
      "id": 5261741,
      "name": "La Equidad",
      "slug": "la-equidad",
      "team_type": "Main",
      "reputation": {
        "home": 5000,
        "national": 5000,
        "world": 5000
      }
    },
    {
      "id": 88500023,
      "name": "La Equidad",
      "slug": "la-equidad-u20",
      "team_type": "U20",
      "reputation": {
        "home": 1500,
        "national": 1500,
        "world": 1500
      }
    },
    {
      "id": 88500024,
      "name": "La Equidad",
      "slug": "la-equidad-u18",
      "team_type": "U18",
      "reputation": {
        "home": 1000,
        "national": 1000,
        "world": 1000
      }
    }
  ],
  "colors": {
    "background": "#195d48",
    "foreground": "#ffffff"
  },
  "philosophy": "Balanced",
  "facilities": {
    "training": "Average",
    "youth": "Average",
    "academy": "Adequate",
    "recruitment": "Good"
  },
  "average_attendance": 5701,
  "ids": {
    "transfermarkt.com": "17425"
  }
}
