{
  "id": 2000291244,
  "first_name": "Edoardo",
  "last_name": "Zaia",
  "birth_date": "2006-09-12",
  "country_id": 776,
  "club_id": 1174,
  "positions": [
    {
      "code": "ST",
      "level": 20
    }
  ],
  "foots": {
    "left": 50,
    "right": 100
  },
  "current_ability": 64,
  "potential_ability": -55,
  "value": 12000,
  "contract": {    "expiration": "2026-06-30",
    "started": "2025-07-01",
    "contract_type": "FullTime"
  },
  "ids": {
    "transfermarkt.com": "985849"
  }
}