{
  "id": 71100094,
  "name": "Polissia",
  "location": {
    "city_id": 1709
  },
  "finance": {
    "balance": 1905000
  },
  "teams": [
    {
      "id": 71100094,
      "name": "Polissia",
      "slug": "polissia-zhytomyr",
      "team_type": "Main",
      "reputation": {
        "home": 4400,
        "national": 4400,
        "world": 4400
      }
    },
    {
      "id": 88700019,
      "name": "Polissia",
      "slug": "polissia-zhytomyr-u21",
      "team_type": "U21",
      "reputation": {
        "home": 1320,
        "national": 1320,
        "world": 1320
      }
    },
    {
      "id": 88700020,
      "name": "Polissia",
      "slug": "polissia-zhytomyr-u19",
      "team_type": "U19",
      "reputation": {
        "home": 880,
        "national": 880,
        "world": 880
      }
    }
  ],
  "colors": {
    "background": "#195d48",
    "foreground": "#ffffff"
  },
  "philosophy": "Balanced",
  "facilities": {
    "training": "Great",
    "youth": "Good",
    "academy": "Average",
    "recruitment": "Adequate"
  },
  "average_attendance": 2900,
  "ids": {
    "transfermarkt.com": "53646"
  }
}