{
  "id": 14150751,
  "first_name": "Nicolás",
  "last_name": "Zalazar",
  "birth_date": "1997-01-29",
  "country_id": 1649,
  "club_id": 108510,
  "positions": [
    {
      "code": "DC",
      "level": 20
    }
  ],
  "foots": {
    "left": 40,
    "right": 100
  },
  "current_ability": 118,
  "potential_ability": 118,
  "value": 2000000,
  "contract": {
    "salary": 104000,
    "expiration": "2026-12-31",
    "started": "2025-07-01",
    "contract_type": "FullTime"
  },
  "ids": {
    "transfermarkt.com": "471640"
  }
}