{
  "id": 2000276944,
  "first_name": "Anton",
  "last_name": "Zalamay",
  "birth_date": "2007-08-01",
  "country_id": 758,
  "club_id": 17004083,
  "positions": [
    {
      "code": "MC",
      "level": 20
    },
    {
      "code": "MR",
      "level": 20
    },
    {
      "code": "AMC",
      "level": 20
    }
  ],
  "foots": {
    "left": 45,
    "right": 100
  },
  "current_ability": 60,
  "potential_ability": -45,
  "value": 10000,
  "contract": {
    "salary": 1144,
    "expiration": "2026-06-30",
    "started": "2025-07-01",
    "contract_type": "FullTime"
  }
}