{
  "id": 53124625,
  "first_name": "Julian",
  "last_name": "Faye Lund",
  "birth_date": "1999-05-20",
  "country_id": 786,
  "club_id": 1293,
  "positions": [
    {
      "code": "GK",
      "level": 20
    }
  ],
  "foots": {
    "left": 25,
    "right": 100
  },
  "current_ability": 106,
  "potential_ability": 120,
  "value": 363000,
  "contract": {    "expiration": "2026-12-31",
    "started": "2025-07-01",
    "contract_type": "FullTime"
  },
  "ids": {
    "transfermarkt.com": "358726"
  }
}