{
  "id": 2000017872,
  "first_name": "Dirk",
  "last_name": "Baron",
  "birth_date": "2002-08-16",
  "country_id": 784,
  "club_id": 1007,
  "positions": [
    {
      "code": "GK",
      "level": 20
    }
  ],
  "foots": {
    "left": 50,
    "right": 100
  },
  "current_ability": 86,
  "potential_ability": 106,
  "value": 15000,
  "contract": {
    "salary": 38168,
    "expiration": "2026-06-30",
    "started": "2025-07-01",
    "contract_type": "FullTime"
  },
  "ids": {
    "transfermarkt.com": "747635"
  }
}