{
  "id": 43500889,
  "first_name": "Gioele",
  "last_name": "Zacchi",
  "birth_date": "2003-07-10",
  "country_id": 776,
  "club_id": 3800256,
  "positions": [
    {
      "code": "GK",
      "level": 20
    }
  ],
  "foots": {
    "left": 50,
    "right": 100
  },
  "current_ability": 100,
  "potential_ability": 136,
  "value": 2000000,
  "contract": {
    "salary": 260000,
    "expiration": "2029-06-30",
    "started": "2025-07-01",
    "contract_type": "FullTime"
  },
  "ids": {
    "transfermarkt.com": "659648"
  }
}