{
  "id": 2000106738,
  "first_name": "Yovany",
  "last_name": "García",
  "birth_date": "2003-07-06",
  "country_id": 1653,
  "club_id": 2200063,
  "positions": [
    {
      "code": "DM",
      "level": 20
    },
    {
      "code": "MC",
      "level": 20
    }
  ],
  "foots": {
    "left": 40,
    "right": 100
  },
  "current_ability": 76,
  "potential_ability": 110,
  "value": 0,
  "contract": {    "expiration": "2027-12-31",
    "started": "2025-07-01",
    "contract_type": "Amateur"
  }
}