{
  "id": 2000518492,
  "first_name": "Grant",
  "last_name": "Leveille",
  "birth_date": "2008-07-03",
  "country_id": 375,
  "club_id": 1913,
  "positions": [
    {
      "code": "GK",
      "level": 20
    }
  ],
  "foots": {
    "left": 50,
    "right": 100
  },
  "current_ability": 76,
  "potential_ability": -65,
  "value": 1000000,
  "contract": {
    "salary": 52000,
    "expiration": "2029-06-30",
    "started": "2025-07-01",
    "contract_type": "FullTime"
  },
  "ids": {
    "transfermarkt.com": "1457747"
  }
}