{
  "id": 2000311295,
  "first_name": "Gustavo",
  "last_name": "Méndez",
  "birth_date": "2004-03-31",
  "country_id": 1649,
  "club_id": 102476,
  "positions": [
    {
      "code": "MC",
      "level": 20
    },
    {
      "code": "AMC",
      "level": 20
    }
  ],
  "foots": {
    "left": 60,
    "right": 100
  },
  "current_ability": 82,
  "potential_ability": -55,
  "value": 144000,
  "contract": {
    "expiration": "2025-12-31",
    "started": "2025-07-01",
    "contract_type": "FullTime"
  }
}
