{
  "id": 67219031,
  "first_name": "Gonzalo",
  "last_name": "Villar",
  "birth_date": "1998-03-23",
  "country_id": 796,
  "club_id": 1707,
  "positions": [
    {
      "code": "MC",
      "level": 20
    },
    {
      "code": "AMC",
      "level": 20
    }
  ],
  "foots": {
    "left": 65,
    "right": 100
  },
  "current_ability": 120,
  "potential_ability": 136,
  "value": 3000000,
  "contract": {
    "salary": 832000,
    "expiration": "2029-06-30",
    "started": "2025-07-01",
    "contract_type": "FullTime"
  },
  "ids": {
    "transfermarkt.com": "398163"
  },
  "history": [
    { "s": 2019, "c": 1100, "p": 3 },
    { "s": 2020, "c": 1100, "p": 39 },
    { "s": 2021, "c": 1710, "p": 10 },
    { "s": 2022, "c": 1167, "p": 15 },
    { "s": 2022, "c": 1710, "p": 16 },
    { "s": 2023, "c": 1714, "p": 35, "g": 1 },
    { "s": 2025, "c": 1707, "p": 3 }
  ]
}
