{
  "id": 1749,
  "name": "Zaragoza",
  "location": {
    "city_id": 627
  },
  "finance": {
    "balance": 12700000
  },
  "teams": [
    {
      "id": 1749,
      "name": "Zaragoza",
      "slug": "zaragoza",
      "team_type": "Main",
      "reputation": {
        "home": 6200,
        "national": 6200,
        "world": 6200
      }
    },
    {
      "id": 99700015,
      "name": "Zaragoza",
      "slug": "zaragoza-u20",
      "team_type": "U20",
      "reputation": {
        "home": 1860,
        "national": 1860,
        "world": 1860
      }
    },
    {
      "id": 99700016,
      "name": "Zaragoza",
      "slug": "zaragoza-u18",
      "team_type": "U18",
      "reputation": {
        "home": 1240,
        "national": 1240,
        "world": 1240
      }
    }
  ],
  "colors": {
    "background": "#003da5",
    "foreground": "#ffffff"
  },
  "philosophy": "Balanced",
  "facilities": {
    "training": "Great",
    "youth": "Great",
    "academy": "Good",
    "recruitment": "Average"
  },
  "average_attendance": 18000,
  "ids": {
    "transfermarkt.com": "142"
  }
}
