{
  "id": 2000198591,
  "first_name": "Murray",
  "last_name": "Campbell",
  "birth_date": "2006-07-25",
  "country_id": 793,
  "club_id": 622,
  "positions": [
    {
      "code": "DC",
      "level": 20
    }
  ],
  "foots": {
    "left": 100,
    "right": 50
  },
  "current_ability": 86,
  "potential_ability": -6,
  "value": 433000,
  "contract": {
    "salary": 26000,
    "expiration": "2027-06-30",
    "started": "2025-07-01",
    "contract_type": "FullTime"
  },
  "ids": {
    "transfermarkt.com": "948915"
  }
}