{
  "id": 42074305,
  "first_name": "Assaf",
  "last_name": "Tzur",
  "birth_date": "1998-08-28",
  "country_id": 775,
  "club_id": 1090,
  "positions": [
    {
      "code": "GK",
      "level": 20
    }
  ],
  "foots": {
    "left": 40,
    "right": 100
  },
  "current_ability": 110,
  "potential_ability": 136,
  "value": 554000,
  "contract": {
    "salary": 260000,
    "expiration": "2027-05-31",
    "started": "2025-07-01",
    "contract_type": "FullTime"
  },
  "ids": {
    "transfermarkt.com": "489614"
  }
}