{
  "id": 13211674,
  "enabled": true,
  "slug": "chadian-premier-division",
  "name": "Premier Division",
  "reputation": 1500,
  "tier": 1,
  "promotion_spots": 0,
  "relegation_spots": 2,
  "sub_leagues_competitions": ["U18"],
  "settings": {
    "season_starting_half": {
      "from_day": 1,
      "from_month": 10,
      "to_day": 20,
      "to_month": 12
    },
    "season_ending_half": {
      "from_day": 15,
      "from_month": 1,
      "to_day": 30,
      "to_month": 6
    }
  },
  "foreign_players": []
}
