{
  "id": 2000275054,
  "first_name": "Niall",
  "last_name": "McAndrew",
  "birth_date": "2007-05-02",
  "country_id": 789,
  "club_id": 645,
  "positions": [
    {
      "code": "AMR",
      "level": 20
    },
    {
      "code": "AML",
      "level": 20
    },
    {
      "code": "AMC",
      "level": 20
    }
  ],
  "current_ability": 70,
  "potential_ability": -65,
  "value": 102000,
  "contract": {
    "salary": 26000,
    "expiration": "2027-06-30",
    "started": "2025-07-01",
    "contract_type": "FullTime"
  }
}