{
  "id": 2000124136,
  "first_name": "Egas",
  "last_name": "Cacintura",
  "birth_date": "1997-10-29",
  "country_id": 6,
  "club_id": 58137861,
  "positions": [
    {
      "code": "MC",
      "level": 20
    },
    {
      "code": "MR",
      "level": 20
    },
    {
      "code": "ML",
      "level": 20
    },
    {
      "code": "AMR",
      "level": 20
    },
    {
      "code": "AML",
      "level": 20
    },
    {
      "code": "AMC",
      "level": 20
    },
    {
      "code": "ST",
      "level": 20
    }
  ],
  "foots": {
    "left": 50,
    "right": 100
  },
  "current_ability": 122,
  "potential_ability": 122,
  "value": 2000000,
  "contract": {    "expiration": "2028-06-10",
    "started": "2025-07-01",
    "contract_type": "FullTime"
  },
  "ids": {
    "transfermarkt.com": "911400"
  },
  "history": [
    { "s": 2021, "c": 58064627, "p": 27 },
    { "s": 2024, "c": 58046584, "p": 26, "g": 4 },
    { "s": 2025, "c": 58137861, "p": 20, "g": 7 }
  ]
}