{
  "id": 2000225259,
  "first_name": "Ruslan",
  "last_name": "Cherviakov",
  "birth_date": "2005-02-18",
  "country_id": 791,
  "club_id": 58117053,
  "positions": [
    {
      "code": "MR",
      "level": 20
    },
    {
      "code": "AMR",
      "level": 20
    },
    {
      "code": "AML",
      "level": 20
    }
  ],
  "foots": {
    "left": 35,
    "right": 100
  },
  "current_ability": 92,
  "potential_ability": -65,
  "value": 653000,
  "contract": {    "expiration": "2026-06-30",
    "started": "2025-07-01",
    "contract_type": "FullTime"
  }
}