{
  "id": 2000495181,
  "first_name": "Abdul",
  "last_name": "Mumini Salifu",
  "birth_date": "2004-09-13",
  "country_id": 21,
  "club_id": 13117239,
  "positions": [
    {
      "code": "DM",
      "level": 20
    },
    {
      "code": "MC",
      "level": 20
    }
  ],
  "foots": {
    "left": 40,
    "right": 100
  },
  "current_ability": 62,
  "potential_ability": 80,
  "value": 11000,
  "contract": {    "expiration": "2026-06-30",
    "started": "2025-07-01",
    "contract_type": "FullTime"
  }
}