{
  "id": 2000272649,
  "first_name": "Kaique",
  "last_name": "Kenji",
  "birth_date": "2006-01-30",
  "country_id": 1651,
  "club_id": 321,
  "positions": [
    {
      "code": "AML",
      "level": 20
    },
    {
      "code": "ST",
      "level": 20
    }
  ],
  "foots": {
    "left": 60,
    "right": 100
  },
  "current_ability": 108,
  "potential_ability": -75,
  "value": 4000000,
  "contract": {    "expiration": "2028-12-31",
    "started": "2025-07-01",
    "contract_type": "FullTime"
  },
  "ids": {
    "transfermarkt.com": "1253814"
  }
}