{
  "id": 2000393413,
  "first_name": "Guilliano",
  "last_name": "Cairo",
  "birth_date": "2006-03-18",
  "country_id": 784,
  "club_id": 1004,
  "positions": [
    {
      "code": "DR",
      "level": 20
    },
    {
      "code": "DC",
      "level": 20
    }
  ],
  "foots": {
    "left": 50,
    "right": 100
  },
  "current_ability": 84,
  "potential_ability": -6,
  "value": 232000,
  "contract": {    "expiration": "2027-06-30",
    "started": "2025-07-01",
    "contract_type": "FullTime"
  }
}