{
  "id": 67272780,
  "first_name": "Samuel",
  "last_name": "Obeng",
  "birth_date": "1997-05-15",
  "country_id": 21,
  "club_id": 1660,
  "positions": [
    {
      "code": "AML",
      "level": 20
    },
    {
      "code": "ST",
      "level": 20
    }
  ],
  "foots": {
    "left": 100,
    "right": 60
  },
  "current_ability": 108,
  "potential_ability": 120,
  "value": 167000,
  "contract": {    "expiration": "2027-06-30",
    "started": "2025-07-01",
    "contract_type": "FullTime"
  },
  "ids": {
    "transfermarkt.com": "522719"
  },
  "history": [
    { "s": 2024, "c": 2443, "p": 11, "g": 1 }
  ]
}