{
  "id": 12088452,
  "first_name": "Daouda",
  "last_name": "Guindo",
  "birth_date": "2002-10-14",
  "country_id": 31,
  "club_id": 2061,
  "positions": [
    {
      "code": "DL",
      "level": 20
    },
    {
      "code": "DC",
      "level": 20
    }
  ],
  "foots": {
    "left": 100,
    "right": 40
  },
  "current_ability": 116,
  "potential_ability": 142,
  "value": 3000000,
  "contract": {    "expiration": "2026-06-30",
    "started": "2025-07-01",
    "contract_type": "FullTime"
  },
  "ids": {
    "transfermarkt.com": "671590"
  },
  "history": [
    { "s": 2025, "c": 2061, "p": 20 }
  ]
}