{
  "id": 2000039978,
  "first_name": "Lars",
  "last_name": "Villiger",
  "birth_date": "2003-04-29",
  "country_id": 798,
  "club_id": 1851,
  "positions": [
    {
      "code": "ST",
      "level": 20
    }
  ],
  "foots": {
    "left": 60,
    "right": 100
  },
  "current_ability": 114,
  "potential_ability": 130,
  "value": 1000000,
  "contract": {    "expiration": "2028-06-30",
    "started": "2025-07-01",
    "contract_type": "FullTime"
  },
  "ids": {
    "transfermarkt.com": "707759"
  }
}