{
  "id": 45090780,
  "first_name": "Mateus",
  "last_name": "Castro",
  "birth_date": "1994-09-11",
  "country_id": 1651,
  "club_id": 1191,
  "positions": [
    {
      "code": "AMR",
      "level": 20
    },
    {
      "code": "AML",
      "level": 20
    },
    {
      "code": "AMC",
      "level": 20
    },
    {
      "code": "FC",
      "level": 20
    }
  ],
  "current_ability": 122,
  "potential_ability": 136,
  "value": 982000,
  "contract": {
    "salary": 988000,
    "expiration": "2027-06-30",
    "started": "2025-07-01",
    "contract_type": "FullTime"
  },
  "ids": {
    "transfermarkt.com": "334828"
  }
}