{
  "id": 2000091490,
  "first_name": "Tadeo",
  "last_name": "Allende",
  "birth_date": "1999-02-20",
  "country_id": 1649,
  "club_id": 72052048,
  "positions": [
    {
      "code": "AMR",
      "level": 20
    },
    {
      "code": "AML",
      "level": 20
    },
    {
      "code": "ST",
      "level": 20
    }
  ],
  "foots": {
    "left": 60,
    "right": 100
  },
  "current_ability": 122,
  "potential_ability": 138,
  "value": 3000000,
  "contract": {
    "salary": 5772000,
    "expiration": "2030-06-30",
    "started": "2025-07-01",
    "contract_type": "FullTime"
  }
}
