{
  "id": 91004704,
  "first_name": "Daniel",
  "last_name": "Batz",
  "birth_date": "1991-01-12",
  "country_id": 771,
  "club_id": 918,
  "positions": [
    {
      "code": "GK",
      "level": 20
    }
  ],
  "foots": {
    "left": 35,
    "right": 100
  },
  "current_ability": 128,
  "potential_ability": 130,
  "value": 1000000,
  "contract": {
    "salary": 416000,
    "expiration": "2026-06-30",
    "started": "2025-07-01",
    "contract_type": "FullTime"
  },
  "ids": {
    "transfermarkt.com": "90317"
  },
  "history": [
    { "s": 2023, "c": 918, "p": 4 },
    { "s": 2025, "c": 918, "p": 15 }
  ]
}