{
  "id": 85133955,
  "first_name": "Jérémy",
  "last_name": "Gélin",
  "birth_date": "1997-04-24",
  "country_id": 769,
  "club_id": 827,
  "positions": [
    {
      "code": "DC",
      "level": 20
    },
    {
      "code": "DM",
      "level": 20
    },
    {
      "code": "MC",
      "level": 20
    }
  ],
  "foots": {
    "left": 50,
    "right": 100
  },
  "current_ability": 116,
  "potential_ability": 120,
  "value": 943000,
  "contract": {    "expiration": "2026-06-30",
    "started": "2025-07-01",
    "contract_type": "FullTime"
  }
}