{
  "id": 27119214,
  "first_name": "Jeppe",
  "last_name": "Okkels",
  "birth_date": "1999-07-27",
  "country_id": 764,
  "club_id": 1787,
  "positions": [
    {
      "code": "ML",
      "level": 20
    },
    {
      "code": "AMR",
      "level": 20
    },
    {
      "code": "AML",
      "level": 20
    }
  ],
  "foots": {
    "left": 50,
    "right": 100
  },
  "current_ability": 114,
  "potential_ability": 130,
  "value": 1000000,
  "contract": {
    "salary": 104000,
    "expiration": "2028-12-31",
    "started": "2025-07-01",
    "contract_type": "FullTime"
  },
  "ids": {
    "transfermarkt.com": "345591"
  },
  "history": [
    { "s": 2023, "c": 1010, "p": 5 }
  ]
}