{
  "id": 2000024038,
  "first_name": "Federico",
  "last_name": "Accornero",
  "birth_date": "2004-02-05",
  "country_id": 776,
  "club_id": 1116,
  "positions": [
    {
      "code": "AML",
      "level": 20
    },
    {
      "code": "AMC",
      "level": 20
    }
  ],
  "foots": {
    "left": 50,
    "right": 100
  },
  "current_ability": 100,
  "potential_ability": 126,
  "value": 739000,
  "contract": {    "expiration": "2028-06-30",
    "started": "2025-07-01",
    "contract_type": "FullTime"
  },
  "ids": {
    "transfermarkt.com": "650999"
  },
  "history": [
    { "s": 2024, "c": 1132, "p": 1 }
  ]
}