{
  "id": 2000417456,
  "first_name": "Elijah",
  "last_name": "Addai",
  "birth_date": "2000-03-19",
  "country_id": 21,
  "club_id": 47001127,
  "positions": [
    {
      "code": "AMR",
      "level": 20
    },
    {
      "code": "AML",
      "level": 20
    },
    {
      "code": "AMC",
      "level": 20
    }
  ],
  "foots": {
    "left": 100,
    "right": 60
  },
  "current_ability": 76,
  "potential_ability": 90,
  "value": 67000,
  "contract": {    "expiration": "2026-12-31",
    "started": "2025-07-01",
    "contract_type": "FullTime"
  }
}