{
  "id": 2000464164,
  "first_name": "Dušan",
  "last_name": "Žagar",
  "birth_date": "2006-10-28",
  "country_id": 802,
  "club_id": 62030404,
  "positions": [
    {
      "code": "AML",
      "level": 20
    },
    {
      "code": "AMC",
      "level": 20
    },
    {
      "code": "ST",
      "level": 20
    }
  ],
  "foots": {
    "left": 35,
    "right": 100
  },
  "current_ability": 88,
  "potential_ability": -65,
  "value": 295000,
  "contract": {    "expiration": "2027-06-30",
    "started": "2025-07-01"
  },
  "ids": {
    "transfermarkt.com": "999057"
  }
}