{
  "id": 41053579,
  "first_name": "Rifad",
  "last_name": "Marasabessy",
  "birth_date": "1999-07-07",
  "country_id": 113,
  "club_id": 5622736,
  "positions": [
    {
      "code": "DR",
      "level": 20
    },
    {
      "code": "WBR",
      "level": 20
    }
  ],
  "foots": {
    "left": 50,
    "right": 100
  },
  "current_ability": 80,
  "potential_ability": 82,
  "value": 26000,
  "contract": {    "expiration": "2026-07-01",
    "started": "2025-07-01",
    "contract_type": "FullTime"
  }
}