{
  "id": 2000026484,
  "first_name": "Louis",
  "last_name": "Mouquet",
  "birth_date": "2004-07-21",
  "country_id": 769,
  "club_id": 1154,
  "positions": [
    {
      "code": "GK",
      "level": 20
    }
  ],
  "foots": {
    "left": 45,
    "right": 100
  },
  "current_ability": 70,
  "potential_ability": 100,
  "value": 30000,
  "contract": {    "expiration": "2028-06-30",
    "started": "2025-07-01",
    "contract_type": "FullTime"
  },
  "ids": {
    "transfermarkt.com": "810067"
  }
}