{
  "id": 2000296473,
  "first_name": "Maj",
  "last_name": "Blažič",
  "birth_date": "2007-01-25",
  "country_id": 795,
  "club_id": 1126,
  "positions": [
    {
      "code": "MC",
      "level": 20
    },
    {
      "code": "AMC",
      "level": 20
    }
  ],
  "foots": {
    "left": 50,
    "right": 100
  },
  "current_ability": 86,
  "potential_ability": -65,
  "value": 352000,
  "contract": {    "expiration": "2027-06-30",
    "started": "2025-07-01",
    "contract_type": "FullTime"
  }
}