{
  "id": 2000240946,
  "first_name": "Stanislav",
  "last_name": "Poroikov",
  "birth_date": "2004-04-24",
  "country_id": 791,
  "club_id": 58127493,
  "positions": [
    {
      "code": "DR",
      "level": 20
    },
    {
      "code": "WBR",
      "level": 20
    },
    {
      "code": "MR",
      "level": 20
    },
    {
      "code": "AMR",
      "level": 20
    }
  ],
  "foots": {
    "left": 60,
    "right": 100
  },
  "current_ability": 92,
  "potential_ability": -6,
  "value": 539000,
  "contract": {    "expiration": "2027-06-30",
    "started": "2025-07-01",
    "contract_type": "FullTime"
  }
}