{
  "id": 2000434359,
  "first_name": "Kabiru",
  "last_name": "Abdullahi",
  "birth_date": "1994-11-20",
  "country_id": 38,
  "club_id": 5340758,
  "positions": [
    {
      "code": "DC",
      "level": 20
    }
  ],
  "foots": {
    "left": 35,
    "right": 100
  },
  "current_ability": 76,
  "potential_ability": 84,
  "value": 20000,
  "contract": {
    "salary": 832,
    "expiration": "2026-08-31",
    "started": "2025-07-01",
    "contract_type": "FullTime"
  },
  "loan": {
    "to_club_id": 5340763,
    "expiration": "2027-06-30",
    "salary": 832,
    "wage_contribution_pct": 100
  }
}