{
  "id": 2000525764,
  "first_name": "Lungelo",
  "last_name": "Dondolo",
  "birth_date": "2006-10-25",
  "country_id": 45,
  "club_id": 1645,
  "positions": [
    {
      "code": "AMC",
      "level": 20
    }
  ],
  "foots": {
    "left": 55,
    "right": 100
  },
  "current_ability": 76,
  "potential_ability": -55,
  "value": 34000,
  "contract": {    "expiration": "2026-06-30",
    "started": "2025-07-01"
  },
  "loan": {
    "to_club_id": 2000471814,
    "expiration": "2027-06-30",    "wage_contribution_pct": 100
  }
}