{
  "id": 2000205785,
  "first_name": "Oumar",
  "last_name": "Pona",
  "birth_date": "2006-06-21",
  "country_id": 31,
  "club_id": 875,
  "positions": [
    {
      "code": "GK",
      "level": 20
    }
  ],
  "current_ability": 96,
  "potential_ability": -7,
  "value": 1000000,
  "contract": {
    "salary": 52000,
    "expiration": "2027-06-30",
    "started": "2025-07-01",
    "contract_type": "FullTime"
  },
  "ids": {
    "transfermarkt.com": "1073176"
  },
  "history": [
    { "s": 2025, "c": 875, "p": 2 }
  ]
}