{
  "id": 2000094711,
  "first_name": "Sharafi",
  "last_name": "Al-Saleem",
  "birth_date": "1999-08-16",
  "country_id": 133,
  "club_id": 7920360,
  "positions": [
    {
      "code": "DM",
      "level": 20
    },
    {
      "code": "MC",
      "level": 20
    }
  ],
  "foots": {
    "left": 50,
    "right": 100
  },
  "current_ability": 76,
  "potential_ability": 86,
  "value": 93000,
  "contract": {    "expiration": "2027-06-30",
    "started": "2025-07-01",
    "contract_type": "PartTime"
  }
}
