{
  "id": 67176059,
  "first_name": "Iván",
  "last_name": "Alejo",
  "birth_date": "1995-02-10",
  "country_id": 796,
  "club_id": 1747,
  "positions": [
    {
      "code": "DR",
      "level": 20
    },
    {
      "code": "WBR",
      "level": 20
    },
    {
      "code": "MR",
      "level": 20
    },
    {
      "code": "AMR",
      "level": 20
    }
  ],
  "foots": {
    "left": 45,
    "right": 100
  },
  "current_ability": 126,
  "potential_ability": 130,
  "value": 5000000,
  "contract": {    "expiration": "2027-06-30",
    "started": "2025-07-01",
    "contract_type": "FullTime"
  },
  "ids": {
    "transfermarkt.com": "281755"
  },
  "history": [
    { "s": 2017, "c": 1753, "p": 22, "g": 1 },
    { "s": 2018, "c": 1710, "p": 4 },
    { "s": 2020, "c": 1682, "p": 22, "g": 1 },
    { "s": 2021, "c": 1682, "p": 20, "g": 2 },
    { "s": 2022, "c": 1682, "p": 31 },
    { "s": 2023, "c": 1682, "p": 30 }
  ]
}