{
  "id": 2000075986,
  "first_name": "Brite",
  "last_name": "Ihuomah",
  "birth_date": "2003-02-17",
  "country_id": 782,
  "club_id": 1247,
  "positions": [
    {
      "code": "MC",
      "level": 20
    },
    {
      "code": "AMC",
      "level": 20
    }
  ],
  "foots": {
    "left": 40,
    "right": 100
  },
  "current_ability": 40,
  "potential_ability": 68,
  "value": 6000,
  "contract": {    "expiration": "2026-05-31",
    "started": "2025-07-01",
    "contract_type": "PartTime"
  },
  "loan": {
    "to_club_id": 1251,
    "expiration": "2027-05-31",    "wage_contribution_pct": 100
  }
}