{
  "id": 35017377,
  "first_name": "Oliver",
  "last_name": "Baumann",
  "birth_date": "1990-06-02",
  "country_id": 771,
  "club_id": 879226,
  "positions": [
    {
      "code": "GK",
      "level": 20
    }
  ],
  "foots": {
    "left": 35,
    "right": 100
  },
  "current_ability": 150,
  "potential_ability": 150,
  "contract": {
    "salary": 3900000,
    "expiration": "2028-06-30",
    "started": "2025-07-01",
    "contract_type": "FullTime"
  },
  "ids": {
    "transfermarkt.com": "55089"
  },
  "history": [
    { "s": 2012, "c": 944, "p": 34 },
    { "s": 2013, "c": 944, "p": 33 },
    { "s": 2014, "c": 879226, "p": 34 },
    { "s": 2015, "c": 879226, "p": 33 },
    { "s": 2016, "c": 879226, "p": 34 },
    { "s": 2017, "c": 879226, "p": 34 },
    { "s": 2018, "c": 879226, "p": 33 },
    { "s": 2019, "c": 879226, "p": 30 },
    { "s": 2020, "c": 879226, "p": 31 },
    { "s": 2021, "c": 879226, "p": 33 },
    { "s": 2022, "c": 879226, "p": 34 },
    { "s": 2023, "c": 879226, "p": 34 },
    { "s": 2024, "c": 879226, "p": 28 },
    { "s": 2025, "c": 879226, "p": 27 }
  ]
}