{
  "id": 2000281571,
  "first_name": "Yael",
  "last_name": "Padilla",
  "birth_date": "2005-12-19",
  "country_id": 379,
  "club_id": 1255,
  "positions": [
    {
      "code": "AMR",
      "level": 20
    },
    {
      "code": "AML",
      "level": 20
    },
    {
      "code": "AMC",
      "level": 20
    }
  ],
  "foots": {
    "left": 60,
    "right": 100
  },
  "current_ability": 106,
  "potential_ability": -75,
  "value": 3000000,
  "contract": {    "expiration": "2026-06-30",
    "started": "2025-07-01",
    "contract_type": "FullTime"
  },
  "ids": {
    "transfermarkt.com": "955756"
  }
}