{
  "id": 2000256649,
  "first_name": "Miłosz",
  "last_name": "Kozik",
  "birth_date": "2004-12-18",
  "country_id": 787,
  "club_id": 96000060,
  "positions": [
    {
      "code": "DC",
      "level": 20
    }
  ],
  "foots": {
    "left": 40,
    "right": 100
  },
  "current_ability": 80,
  "potential_ability": 96,
  "value": 126000,
  "contract": {    "expiration": "2027-06-30",
    "started": "2025-07-01",
    "contract_type": "FullTime"
  },
  "loan": {
    "to_club_id": 714200,
    "expiration": "2027-06-30",    "wage_contribution_pct": 100
  }
}