{
  "id": 58092172,
  "first_name": "Artem",
  "last_name": "Simonyan",
  "birth_date": "1995-02-20",
  "country_id": 754,
  "club_id": 1527,
  "positions": [
    {
      "code": "MC",
      "level": 20
    },
    {
      "code": "AML",
      "level": 20
    },
    {
      "code": "AMC",
      "level": 20
    }
  ],
  "foots": {
    "left": 55,
    "right": 100
  },
  "current_ability": 102,
  "potential_ability": 102,
  "value": 385000,
  "contract": {    "expiration": "2026-06-10",
    "started": "2025-07-01",
    "contract_type": "FullTime"
  },
  "ids": {
    "transfermarkt.com": "235349"
  },
  "history": [
    { "s": 2022, "c": 130498, "p": 2 }
  ]
}