{
  "id": 24016925,
  "first_name": "Mateo",
  "last_name": "Kovačić",
  "birth_date": "1994-05-06",
  "country_id": 761,
  "club_id": 679,
  "positions": [
    {
      "code": "DM",
      "level": 20
    }
  ],
  "current_ability": 152,
  "potential_ability": 172,
  "value": 39000000,
  "contract": {
    "salary": 8580000,
    "expiration": "2027-06-30",
    "started": "2025-07-01",
    "contract_type": "FullTime"
  },
  "ids": {
    "transfermarkt.com": "51471"
  },
  "history": [
    { "s": 2012, "c": 1135, "p": 13 },
    { "s": 2013, "c": 1135, "p": 32 },
    { "s": 2014, "c": 1135, "p": 35, "g": 5 },
    { "s": 2015, "c": 1736, "p": 25 },
    { "s": 2016, "c": 1736, "p": 27, "g": 1 },
    { "s": 2017, "c": 1736, "p": 21 },
    { "s": 2018, "c": 630, "p": 32 },
    { "s": 2019, "c": 630, "p": 31, "g": 1 },
    { "s": 2020, "c": 630, "p": 27 },
    { "s": 2021, "c": 630, "p": 25, "g": 2 },
    { "s": 2022, "c": 630, "p": 27, "g": 1 },
    { "s": 2023, "c": 679, "p": 30, "g": 1 },
    { "s": 2024, "c": 679, "p": 31, "g": 6 },
    { "s": 2025, "c": 679, "p": 1 }
  ]
}
