{
  "id": 19184144,
  "first_name": "Bruno",
  "last_name": "Duarte",
  "birth_date": "1996-03-24",
  "country_id": 1651,
  "club_id": 1955,
  "positions": [
    {
      "code": "AMC",
      "level": 20
    },
    {
      "code": "FC",
      "level": 16
    }
  ],
  "current_ability": 124,
  "potential_ability": 124,
  "value": 2000000,
  "contract": {    "expiration": "2027-06-30",
    "started": "2025-07-01",
    "contract_type": "FullTime"
  },
  "ids": {
    "transfermarkt.com": "598629"
  },
  "history": [
    { "s": 2019, "c": 1494, "p": 19, "g": 5 },
    { "s": 2020, "c": 1494, "p": 29, "g": 5 },
    { "s": 2021, "c": 1494, "p": 31, "g": 7 }
  ]
}