{
  "id": 58092033,
  "first_name": "Ivan",
  "last_name": "Zhitnikov",
  "birth_date": "1995-02-17",
  "country_id": 791,
  "club_id": 477174,
  "positions": [
    {
      "code": "DR",
      "level": 20
    },
    {
      "code": "DL",
      "level": 20
    },
    {
      "code": "WBR",
      "level": 20
    },
    {
      "code": "WBL",
      "level": 20
    },
    {
      "code": "MR",
      "level": 20
    },
    {
      "code": "ML",
      "level": 20
    },
    {
      "code": "AMR",
      "level": 20
    },
    {
      "code": "AML",
      "level": 20
    }
  ],
  "foots": {
    "left": 45,
    "right": 100
  },
  "current_ability": 74,
  "potential_ability": 76,
  "value": 21000,
  "contract": {
    "expiration": "2026-06-30",
    "started": "2025-07-01",
    "contract_type": "FullTime"
  }
}
