{
  "id": 130877,
  "name": "Vitebsk",
  "location": {
    "city_id": 0
  },
  "finance": {
    "balance": 2000000
  },
  "teams": [
    {
      "id": 130877,
      "name": "Vitebsk",
      "slug": "vitebsk",
      "team_type": "Main",
      "reputation": {
        "home": 3200,
        "national": 3200,
        "world": 3200
      }
    },
    {
      "id": 100130877,
      "name": "Vitebsk",
      "slug": "vitebsk-u20",
      "team_type": "U20",
      "reputation": {
        "home": 960,
        "national": 960,
        "world": 960
      }
    },
    {
      "id": 200130877,
      "name": "Vitebsk",
      "slug": "vitebsk-u18",
      "team_type": "U18",
      "reputation": {
        "home": 640,
        "national": 640,
        "world": 640
      }
    }
  ],
  "colors": {
    "background": "#cc0000",
    "foreground": "#003da5"
  },
  "philosophy": "Balanced",
  "facilities": {
    "training": "Adequate",
    "youth": "Average",
    "academy": "Adequate",
    "recruitment": "Average"
  },
  "average_attendance": 897,
  "ids": {
    "transfermarkt.com": "36596"
  }
}
