{
  "id": 15086157,
  "first_name": "Trent",
  "last_name": "Ostler",
  "birth_date": "2002-04-03",
  "country_id": 1435,
  "club_id": 123001,
  "positions": [
    {
      "code": "DR",
      "level": 20
    },
    {
      "code": "WBR",
      "level": 20
    },
    {
      "code": "MR",
      "level": 20
    },
    {
      "code": "AMR",
      "level": 20
    }
  ],
  "foots": {
    "left": 50,
    "right": 100
  },
  "current_ability": 90,
  "potential_ability": 102,
  "value": 170000,
  "contract": {    "expiration": "2027-06-30",
    "started": "2025-07-01",
    "contract_type": "FullTime"
  },
  "ids": {
    "transfermarkt.com": "692320"
  }
}