{
  "id": 16337073,
  "first_name": "Samson",
  "last_name": "Baidoo",
  "birth_date": "2004-03-31",
  "country_id": 755,
  "club_id": 871,
  "positions": [
    {
      "code": "DC",
      "level": 20
    },
    {
      "code": "DM",
      "level": 20
    }
  ],
  "foots": {
    "left": 60,
    "right": 100
  },
  "current_ability": 136,
  "potential_ability": 160,
  "value": 48000000,
  "contract": {    "expiration": "2030-06-30",
    "started": "2025-07-01",
    "contract_type": "FullTime"
  },
  "ids": {
    "transfermarkt.com": "655217"
  },
  "history": [
    { "s": 2025, "c": 871, "p": 18, "g": 2 }
  ]
}