{
  "id": 29232937,
  "first_name": "Jude",
  "last_name": "Bellingham",
  "birth_date": "2003-06-29",
  "country_id": 765,
  "club_id": 1736,
  "positions": [
    {
      "code": "MC",
      "level": 20
    },
    {
      "code": "ML",
      "level": 20
    },
    {
      "code": "AMC",
      "level": 20
    }
  ],
  "foots": {
    "left": 60,
    "right": 100
  },
  "current_ability": 176,
  "potential_ability": 188,
  "value": 173000000,
  "contract": {
    "salary": 17940000,
    "expiration": "2029-06-30",
    "started": "2025-07-01",
    "contract_type": "FullTime"
  },
  "ids": {
    "transfermarkt.com": "581678"
  },
  "history": [
    { "s": 2020, "c": 907, "p": 29, "g": 1 },
    { "s": 2021, "c": 907, "p": 32, "g": 3 },
    { "s": 2022, "c": 907, "p": 31, "g": 8 },
    { "s": 2023, "c": 1736, "p": 28, "g": 19 },
    { "s": 2024, "c": 1736, "p": 31, "g": 9 }
  ]
}
