{
  "id": 144844,
  "name": "Rah Ahan",
  "location": {
    "city_id": 5610
  },
  "finance": {
    "balance": 1270000
  },
  "teams": [
    {
      "id": 144844,
      "name": "Rah Ahan",
      "slug": "rah-ahan",
      "team_type": "Main",
      "reputation": {
        "home": 4000,
        "national": 4000,
        "world": 4000
      }
    },
    {
      "id": 92700021,
      "name": "Rah Ahan",
      "slug": "rah-ahan-u20",
      "team_type": "U20",
      "reputation": {
        "home": 1200,
        "national": 1200,
        "world": 1200
      }
    },
    {
      "id": 92700022,
      "name": "Rah Ahan",
      "slug": "rah-ahan-u18",
      "team_type": "U18",
      "reputation": {
        "home": 800,
        "national": 800,
        "world": 800
      }
    }
  ],
  "colors": {
    "background": "#003da5",
    "foreground": "#e2001a"
  },
  "philosophy": "Balanced",
  "facilities": {
    "training": "Adequate",
    "youth": "Below Average",
    "academy": "Average",
    "recruitment": "Average"
  },
  "average_attendance": 300,
  "ids": {
    "transfermarkt.com": "10684"
  }
}
