{
  "id": 2000045509,
  "first_name": "Antoine",
  "last_name": "Hainaut",
  "birth_date": "2002-02-18",
  "country_id": 769,
  "club_id": 1179,
  "positions": [
    {
      "code": "DR",
      "level": 20
    },
    {
      "code": "WBR",
      "level": 16
    },
    {
      "code": "DM",
      "level": 20
    },
    {
      "code": "AMR",
      "level": 20
    },
    {
      "code": "AMC",
      "level": 20
    }
  ],
  "current_ability": 83,
  "potential_ability": 100,
  "value": 3000000,
  "contract": {    "expiration": "2028-06-30",
    "started": "2025-07-01",
    "contract_type": "FullTime"
  },
  "ids": {
    "transfermarkt.com": "917375"
  },
  "history": [
    { "s": 2024, "c": 1156, "p": 25, "g": 2 }
  ]
}