{
  "id": 67211778,
  "first_name": "Guillermo",
  "last_name": "Vallejo",
  "birth_date": "1995-04-22",
  "country_id": 796,
  "club_id": 67016725,
  "positions": [
    {
      "code": "GK",
      "level": 20
    }
  ],
  "foots": {
    "left": 45,
    "right": 100
  },
  "current_ability": 106,
  "potential_ability": 116,
  "value": 218000,
  "contract": {    "expiration": "2026-06-30",
    "started": "2025-07-01",
    "contract_type": "FullTime"
  },
  "ids": {
    "transfermarkt.com": "341570"
  }
}